setup.py
PyStormLib.egg-info/PKG-INFO
PyStormLib.egg-info/SOURCES.txt
PyStormLib.egg-info/dependency_links.txt
PyStormLib.egg-info/top_level.txt
pystormlib/__init__.py
pystormlib/structure.py
pystormlib/utils.py
pystormlib/winerror.py
pystormlib/ressources/__init__.py
pystormlib/ressources/stormlib_x86.dll