Metadata-Version: 1.1
Name: PyStormLib
Version: 0.1
Summary: Wrapper around Stormlib
Home-page: https://github.com/srounet/pystormlib
Author: Fabien Reboia
Author-email: srounet@gmail.com
License: BSD
Platform: UNKNOWN
Classifier: Programming Language :: Python :: 3.4
Classifier: Environment :: Win32 (MS Windows)
Classifier: Intended Audience :: Developers
Classifier: License :: OSI Approved :: MIT License
